{"_type":"export","__export_format":4,"__export_date":"2024-05-03T15:48:03.351Z","__export_source":"insomnia.desktop.app:v9.1.0","resources":[{"_id":"req_81ea03e324114e7dae91ee337058cbb8","parentId":"fld_6cbb84e073664ec2944f93a6f37aa2c3","modified":1714749826198,"created":1714748744029,"url":"localhost:4000/categorias/1","name":"Deletar Categoria","description":"","method":"DELETE","body":{},"preRequestScript":"","parameters":[],"headers":[{"name":"User-Agent","value":"insomnia/9.1.0"}],"authentication":{},"metaSortKey":-1714748744029,"isPrivate":false,"pathParameters":[],"settingStoreCookies":true,"settingSendCookies":true,"settingDisableRenderRequestBody":false,"settingEncodeUrl":true,"settingRebuildPath":true,"settingFollowRedirects":"global","_type":"request"},{"_id":"fld_6cbb84e073664ec2944f93a6f37aa2c3","parentId":"wrk_c3ff3749a3954958b442797175994891","modified":1714740362938,"created":1714740362938,"name":"categoria","description":"","environment":{},"environmentPropertyOrder":null,"metaSortKey":-1714740362938,"_type":"request_group"},{"_id":"wrk_c3ff3749a3954958b442797175994891","parentId":null,"modified":1714740333103,"created":1714740333103,"name":"Farmacia","description":"","scope":"collection","_type":"workspace"},{"_id":"req_f6e29129a09148fca5ae04f204e72c9d","parentId":"fld_6cbb84e073664ec2944f93a6f37aa2c3","modified":1714750438390,"created":1714748719455,"url":"localhost:4000/categorias/3","name":"Atualizar Categoria","description":"","method":"PUT","body":{"mimeType":"application/json","text":"{ \n\t\"tipo\": \"antialergico\"\n}"},"preRequestScript":"","parameters":[],"headers":[{"name":"Content-Type","value":"application/json"},{"name":"User-Agent","value":"insomnia/9.1.0"}],"authentication":{},"metaSortKey":-1714748719455,"isPrivate":false,"pathParameters":[],"settingStoreCookies":true,"settingSendCookies":true,"settingDisableRenderRequestBody":false,"settingEncodeUrl":true,"settingRebuildPath":true,"settingFollowRedirects":"global","_type":"request"},{"_id":"req_ef091b9b54754581a221cf8fd3f9c13d","parentId":"fld_6cbb84e073664ec2944f93a6f37aa2c3","modified":1714750042257,"created":1714748666525,"url":"http://localhost:4000/categorias","name":"Criar Categoria","description":"","method":"POST","body":{"mimeType":"application/json","text":"{\n\t\"tipo\" : \"cosméticos\"\n}"},"preRequestScript":"","parameters":[],"headers":[{"name":"Content-Type","value":"application/json"},{"name":"User-Agent","value":"insomnia/9.1.0"}],"authentication":{},"metaSortKey":-1714748666525,"isPrivate":false,"pathParameters":[],"settingStoreCookies":true,"settingSendCookies":true,"settingDisableRenderRequestBody":false,"settingEncodeUrl":true,"settingRebuildPath":true,"settingFollowRedirects":"global","_type":"request"},{"_id":"req_c0fbe099425443e3868000c3a04d75d4","parentId":"fld_6cbb84e073664ec2944f93a6f37aa2c3","modified":1714749587080,"created":1714748645003,"url":"localhost:4000/categorias/tipo/antiemetico","name":"Categoria por Tipo","description":"","method":"GET","body":{},"preRequestScript":"","parameters":[],"headers":[{"name":"User-Agent","value":"insomnia/9.1.0"}],"authentication":{},"metaSortKey":-1714748645003,"isPrivate":false,"pathParameters":[],"settingStoreCookies":true,"settingSendCookies":true,"settingDisableRenderRequestBody":false,"settingEncodeUrl":true,"settingRebuildPath":true,"settingFollowRedirects":"global","_type":"request"},{"_id":"req_0760fe0578974ffb89dc764e1db8780f","parentId":"fld_6cbb84e073664ec2944f93a6f37aa2c3","modified":1714748843904,"created":1714748282649,"url":"localhost:4000/categorias/1","name":"Categoria por id","description":"","method":"GET","body":{},"preRequestScript":"","parameters":[],"headers":[{"name":"User-Agent","value":"insomnia/9.1.0"}],"authentication":{},"metaSortKey":-1714748282649,"isPrivate":false,"pathParameters":[],"settingStoreCookies":true,"settingSendCookies":true,"settingDisableRenderRequestBody":false,"settingEncodeUrl":true,"settingRebuildPath":true,"settingFollowRedirects":"global","_type":"request"},{"_id":"req_4f250775c4cd4c5792f76ed3693ad823","parentId":"fld_6cbb84e073664ec2944f93a6f37aa2c3","modified":1714748278689,"created":1714740366200,"url":"http://localhost:4000/categorias","name":"Todas as categorias","description":"","method":"GET","body":{},"preRequestScript":"","parameters":[],"headers":[{"name":"User-Agent","value":"insomnia/9.1.0"}],"authentication":{},"metaSortKey":-1714740366200,"isPrivate":false,"pathParameters":[],"settingStoreCookies":true,"settingSendCookies":true,"settingDisableRenderRequestBody":false,"settingEncodeUrl":true,"settingRebuildPath":true,"settingFollowRedirects":"global","_type":"request"},{"_id":"env_8f706042bd0f1b12cbc6b65878d2fa4ebdbcb62b","parentId":"wrk_c3ff3749a3954958b442797175994891","modified":1714740333122,"created":1714740333122,"name":"Base Environment","data":{},"dataPropertyOrder":null,"color":null,"isPrivate":false,"metaSortKey":1714740333122,"_type":"environment"},{"_id":"jar_8f706042bd0f1b12cbc6b65878d2fa4ebdbcb62b","parentId":"wrk_c3ff3749a3954958b442797175994891","modified":1714740333126,"created":1714740333126,"name":"Default Jar","cookies":[],"_type":"cookie_jar"}]}